LICENSE
MANIFEST.in
README.rst
requirements.txt
setup.py
dependencies_resolver/__init__.py
dependencies_resolver/main.py
dependencies_resolver.egg-info/PKG-INFO
dependencies_resolver.egg-info/SOURCES.txt
dependencies_resolver.egg-info/dependency_links.txt
dependencies_resolver.egg-info/entry_points.txt
dependencies_resolver.egg-info/requires.txt
dependencies_resolver.egg-info/top_level.txt
dependencies_resolver/config/__init__.py
dependencies_resolver/config/__init__.pyc
dependencies_resolver/config/configuration.py
dependencies_resolver/config/configuration.pyc
dependencies_resolver/config/schema.json
dependencies_resolver/dependency_handler/__init__.py
dependencies_resolver/dependency_handler/download.py
dependencies_resolver/dependency_handler/resolve_dependencies.py
dependencies_resolver/dependency_handler/validation.py
dependencies_resolver/schema/__init__.py
dependencies_resolver/schema/loader.py
dependencies_resolver/utils/__init__.py
dependencies_resolver/utils/exception_handler.py
dependencies_resolver/utils/md5_checksum.py
dependencies_resolver/utils/s3_utils.py
tests/dependency_handler/__init__.py
tests/dependency_handler/test_validation.py
tests/utils/__init__.py
tests/utils/test_md5_checksum.py
tests/utils/test_s3_utils.py