Metadata-Version: 1.0
Name: dependencies-resolver
Version: 0.0.11
Summary: Command line tool for downloading dependencies from config file
Home-page: https://github.com/onfido/dependencies-resolver/
Author: Onfido
Author-email: UNKNOWN
License: MIT
Keywords: python,s3,aws,download,binaries,resources,boto3,dependencies,downloader,dependency-management
Platform: UNKNOWN
